civiq6/__init__.py
civiq6/camera.py
civiq6/capture.py
civiq6/devices.py
civiq6/py.typed
civiq6/qt_compat.py
civiq6/version.py
civiq6-0.2.1.dist-info/LICENSE
civiq6-0.2.1.dist-info/METADATA
civiq6-0.2.1.dist-info/WHEEL
civiq6-0.2.1.dist-info/top_level.txt
civiq6-0.2.1.dist-info/RECORD
