Metadata-Version: 2.1
Name: civiq6
Version: 0.2.1
Summary: Package for integrating VimbaPython and Qt6
Home-page: https://github.com/JSS95/civiq6
Author: Jisoo Song
Author-email: jeesoo9595@snu.ac.kr
Maintainer: Jisoo Song
Maintainer-email: jeesoo9595@snu.ac.kr
License: MIT
Classifier: Development Status :: 4 - Beta
Classifier: Intended Audience :: Developers
Classifier: Intended Audience :: Science/Research
Classifier: License :: OSI Approved :: MIT License
Classifier: Operating System :: Microsoft :: Windows
Classifier: Operating System :: POSIX :: Linux
Classifier: Programming Language :: Python
Classifier: Programming Language :: Python :: 3
Classifier: Programming Language :: Python :: 3.7
Classifier: Programming Language :: Python :: 3.8
Classifier: Programming Language :: Python :: 3.9
Classifier: Programming Language :: Python :: 3.10
Classifier: Topic :: Multimedia :: Graphics
Classifier: Topic :: Software Development
Classifier: Topic :: Software Development :: Libraries :: Python Modules
Classifier: Topic :: Software Development :: User Interfaces
Requires-Python: >=3.7
License-File: LICENSE
Provides-Extra: doc
Requires-Dist: numpydoc ; extra == 'doc'
Requires-Dist: sphinx ; extra == 'doc'
Requires-Dist: sphinx-tabs ; extra == 'doc'
Requires-Dist: sphinx-rtd-theme ; extra == 'doc'
Requires-Dist: imageio[ffmpeg] ; extra == 'doc'
Provides-Extra: full
Requires-Dist: sphinx-tabs ; extra == 'full'
Requires-Dist: imageio ; extra == 'full'
Requires-Dist: sphinx-rtd-theme ; extra == 'full'
Requires-Dist: sphinx ; extra == 'full'
Requires-Dist: flake8 ; extra == 'full'
Requires-Dist: numpydoc ; extra == 'full'
Requires-Dist: mypy ; extra == 'full'
Requires-Dist: black ; extra == 'full'
Requires-Dist: imageio[ffmpeg] ; extra == 'full'
Provides-Extra: test
Requires-Dist: black ; extra == 'test'
Requires-Dist: flake8 ; extra == 'test'
Requires-Dist: mypy ; extra == 'test'
Requires-Dist: imageio ; extra == 'test'
